mcbootflash/__init__.py
mcbootflash/__main__.py
mcbootflash/error.py
mcbootflash/flash.py
mcbootflash/protocol.py
mcbootflash/util.py
mcbootflash-10.1.1.dist-info/entry_points.txt
mcbootflash-10.1.1.dist-info/LICENSE
mcbootflash-10.1.1.dist-info/WHEEL
mcbootflash-10.1.1.dist-info/METADATA
mcbootflash-10.1.1.dist-info/RECORD
