Metadata-Version: 2.3
Name: mcbootflash
Version: 10.1.1
Summary: Flash firmware to devices running Microchip's 16-bit bootloader.
Keywords: firmware,flashing,bootloader,serial,uart,microchip,pic24,dspic33,16-bit
Author-email: Alexander Bessman <alexander.bessman@gmail.com>
Requires-Python: >=3.9
Classifier: Programming Language :: Python :: 3
Classifier: Programming Language :: Python :: 3.9
Classifier: Programming Language :: Python :: 3.10
Classifier: Programming Language :: Python :: 3.11
Classifier: Programming Language :: Python :: 3.12
Classifier: Programming Language :: Python :: 3.13
Classifier: Development Status :: 5 - Production/Stable
Classifier: License :: OSI Approved :: MIT License
Requires-Dist: pyserial
Requires-Dist: bincopy >= 20.0.0
Requires-Dist: datastructclass
Requires-Dist: black ; extra == "dev"
Requires-Dist: isort ; extra == "dev"
Requires-Dist: mypy ; extra == "dev"
Requires-Dist: ruff ; extra == "dev"
Requires-Dist: tox ; extra == "dev"
Requires-Dist: mkdocs ; extra == "doc"
Requires-Dist: mkdocs-include-markdown-plugin ; extra == "doc"
Requires-Dist: mkdocstrings[python] ; extra == "doc"
Requires-Dist: mkdocs-material ; extra == "doc"
Requires-Dist: pytest ; extra == "test"
Requires-Dist: coverage ; extra == "test"
Requires-Dist: pytest-reserial>=0.4.0 ; extra == "test"
Project-URL: Home, https://bessman.github.io/mcbootflash/
Provides-Extra: dev
Provides-Extra: doc
Provides-Extra: test
